setup.py
QR_IO.egg-info/PKG-INFO
QR_IO.egg-info/SOURCES.txt
QR_IO.egg-info/dependency_links.txt
QR_IO.egg-info/not-zip-safe
QR_IO.egg-info/requires.txt
QR_IO.egg-info/top_level.txt
bin/qr-io.py
qr_io/__init__.py
qr_io/utils/__init__.py
qr_io/utils/io.py
qr_io/utils/qr.py
qr_io/utils/upload.py
qr_io/web/__init__.py
qr_io/web/views.py