Metadata-Version: 1.0
Name: QR-IO
Version: 0.2
Summary: A utility for using android as stdin device for barcode
Home-page: https://github.com/Hernrup/QR-IO
Author: Mikael Hernrup
Author-email: mikael@hernrup.se
License: MIT
Platform: UNKNOWN
